aws_cdk/asset_node_proxy_agent_v6/_jsii/__init__.py
aws_cdk/asset_node_proxy_agent_v6/_jsii/asset-node-proxy-agent-v6@2.0.3.jsii.tgz
aws_cdk.asset_node_proxy_agent_v6-2.0.3.dist-info/LICENSE
aws_cdk.asset_node_proxy_agent_v6-2.0.3.dist-info/METADATA
aws_cdk.asset_node_proxy_agent_v6-2.0.3.dist-info/NOTICE
aws_cdk.asset_node_proxy_agent_v6-2.0.3.dist-info/WHEEL
aws_cdk.asset_node_proxy_agent_v6-2.0.3.dist-info/top_level.txt
aws_cdk.asset_node_proxy_agent_v6-2.0.3.dist-info/RECORD
