Metadata-Version: 2.1
Name: aws-cdk.asset-node-proxy-agent-v6
Version: 2.0.3
Summary: @aws-cdk/asset-node-proxy-agent-v6
Home-page: https://github.com/cdklabs/awscdk-asset-node-proxy-agent#readme
Author: Amazon Web Services<aws-cdk-dev@amazon.com>
License: Apache-2.0
Project-URL: Source, https://github.com/cdklabs/awscdk-asset-node-proxy-agent.git
Classifier: Intended Audience :: Developers
Classifier: Operating System :: OS Independent
Classifier: Programming Language :: JavaScript
Classifier: Programming Language :: Python :: 3 :: Only
Classifier: Programming Language :: Python :: 3.8
Classifier: Programming Language :: Python :: 3.9
Classifier: Programming Language :: Python :: 3.10
Classifier: Programming Language :: Python :: 3.11
Classifier: Typing :: Typed
Classifier: Development Status :: 5 - Production/Stable
Classifier: License :: OSI Approved
Requires-Python: ~=3.8
License-File: LICENSE
License-File: NOTICE
